[{"Type":"WExpTreasureMapDefinition","Name":"TM_Special_UnderwaterTunnel","Class":"UScriptClass'WExpTreasureMapDefinition'","Properties":{"ZoneId":"Zone.Special.UnderwaterTunnel","Rarity":"EWExpRarity::VeryRare","HowToGetDescription":{"Namespace":"","Key":"FD2403DD42F1AB3A446E4CA73CE2FFC0","SourceString":"Can randomly be found in the marketplace.","LocalizedString":"Can randomly be found in the marketplace."},"SortPriority":900,"IconTextureAssetData":{"AssetPathName":"/Game/UMG/Skybreakers/Textures/Icon_TreasureMap_03.Icon_TreasureMap_03","SubPathString":""},"MaximumStackSize":9999999,"Description":{"Namespace":"","Key":"737D21404CE63B6C892330AE5AB4D09F","SourceString":"Dungeon Key. Grants access to an Underwater Tunnel. Legends say this tunnel was formed by a powerful mage. There is no failure penalty nor a partial completion reward.","LocalizedString":"Dungeon Key. Grants access to an Underwater Tunnel. Legends say this tunnel was formed by a powerful mage. There is no failure penalty nor a partial completion reward."},"DisplayName":{"Namespace":"","Key":"1D5133364C97DE0DF0BBBF8ACB2B4703","SourceString":"Underwater Tunnel Map","LocalizedString":"Underwater Tunnel Map"},"PickupMesh":{"AssetPathName":"/Game/Loot/TreasureMaps/S_TreasureMap_Gold.S_TreasureMap_Gold","SubPathString":""},"ItemBlueprintClass":{"AssetPathName":"/Game/Loot/TreasureMaps/B_TreasureMap_Gold.B_TreasureMap_Gold_C","SubPathString":""}}}]