[{"Type":"WExpTreasureMapDefinition","Name":"TM_Special_PlanetCore","Class":"UScriptClass'WExpTreasureMapDefinition'","Properties":{"ZoneId":"Zone.Special.PlanetCore","Rarity":"EWExpRarity::VeryRare","HowToGetDescription":{"Namespace":"","Key":"E80EF67A4A86257BA13E3D8D4FAA13E1","SourceString":"Can randomly be found in the marketplace.","LocalizedString":"Can randomly be found in the marketplace."},"SortPriority":900,"IconTextureAssetData":{"AssetPathName":"/Game/UMG/Skybreakers/Textures/Icon_TreasureMap_01.Icon_TreasureMap_01","SubPathString":""},"MaximumStackSize":9999999,"Description":{"Namespace":"","Key":"272BF3DD4224B5309925B4947CE31445","SourceString":"Dungeon Key. Grants access to the Planet's Core. Its entrance was once thought to be a cave of wonders. There is no failure penalty nor a partial completion reward.","LocalizedString":"Dungeon Key. Grants access to the Planet's Core. Its entrance was once thought to be a cave of wonders. There is no failure penalty nor a partial completion reward."},"DisplayName":{"Namespace":"","Key":"1C59F4044D3228DC150F56A38FB69C63","SourceString":"Planet's Core Map","LocalizedString":"Planet's Core Map"},"PickupMesh":{"AssetPathName":"/Game/Loot/TreasureMaps/S_TreasureMap_Gold.S_TreasureMap_Gold","SubPathString":""},"ItemBlueprintClass":{"AssetPathName":"/Game/Loot/TreasureMaps/B_TreasureMap_Gold.B_TreasureMap_Gold_C","SubPathString":""}}}]