[{"Type":"LearningCue","Name":"LC_Combat_BossColorShift","Class":"UScriptClass'LearningCue'","Properties":{"TargetEvent":{"TagName":"Combat.Player.BossColorShift"},"VisualizerClass":{"ObjectName":"BlueprintGeneratedClass'B_CombatPointerVisualizer_C'","ObjectPath":"WorldExplorers/Content/Onboarding/Visualizers/B_CombatPointerVisualizer.1"},"TextPayload":{"Namespace":"","Key":"13288C954F0503B08631FF87D426FBF1","SourceString":"The boss has taken control of the board color! Bosses can temporarily lock the elemental power of the room to their element. Tread carefully!","LocalizedString":"The boss has taken control of the board color! Bosses can temporarily lock the elemental power of the room to their element. Tread carefully!"}}}]