[{"Type":"WExpHammerChestDefinition","Name":"HC_MTX_Rare","Class":"UScriptClass'WExpHammerChestDefinition'","Properties":{"TapsToBreak":15,"OnDamageLootPackage":"LTG.HammerChest.MTX.Rare.Hit","OnCompletionLootPackage":"LTG.HammerChest.MTX.Rare.Destroy","Rarity":"EWExpRarity::VeryRare","IconTextureAssetData":{"AssetPathName":"/Game/UMG/Store/Textures/Chest.Chest","SubPathString":""},"Description":{"Namespace":"","Key":"C145E7D54858D1787D25C3B3F18BEE53","SourceString":"Contains gems.","LocalizedString":"Contains gems."},"DisplayName":{"Namespace":"","Key":"6B34DFFA47973AC420A7CDBC4D08E150","SourceString":"Rare Gem Hammer Chest","LocalizedString":"Rare Gem Hammer Chest"}}}]