[{"Type":"WExpHammerChestDefinition","Name":"HC_Upgrade_Mana_Rare","Class":"UScriptClass'WExpHammerChestDefinition'","Properties":{"TapsToBreak":12,"OnDamageLootPackage":"LTG.HammerChest.Upgrade.Mana.Rare.Hit","OnCompletionLootPackage":"LTG.HammerChest.Upgrade.Mana.Rare.Destroy","Rarity":"EWExpRarity::VeryRare","IconTextureAssetData":{"AssetPathName":"/Game/UMG/Store/Textures/Chest.Chest","SubPathString":""},"Description":{"Namespace":"","Key":"A7627CA84CE9DAC8198A449E61FA1136","SourceString":"Contains mana elixirs.","LocalizedString":"Contains mana elixirs."},"DisplayName":{"Namespace":"","Key":"542AAF1A4824941DE52D5799F26753A2","SourceString":"Rare Mana Elixir Hammer Chest","LocalizedString":"Rare Mana Elixir Hammer Chest"}}}]