[{"Type":"WExpUnlockableDefinition","Name":"Unlockable_Skills","Class":"UScriptClass'WExpUnlockableDefinition'","Properties":{"MenuReference":"EWExpMainSubMenus::Team","UpgradeTabReference":"EWExpUpgradeTabs::Skill","RequiredZoneDefinition":{"ObjectName":"WExpZoneDefinition'Zone_OasisOfLife_Map1'","ObjectPath":"WorldExplorers/Content/Campaign/Zones/OasisOfLife/Zone_OasisOfLife_Map1.0"},"ShortDescription":{"Namespace":"","Key":"779A0A58410B0ACCFC2FC9ACEC534E99","SourceString":"Hero Skill Upgrades Unlocked!","LocalizedString":"Hero Skill Upgrades Unlocked!"},"bCanUseItem":false,"Description":{"Namespace":"","Key":"493A3B8148742539FB59A499BDA26FAA","SourceString":"You can now upgrade the skills of your Heroes!","LocalizedString":"You can now upgrade the skills of your Heroes!"},"DisplayName":{"Namespace":"","Key":"CD2F2D0C4E02F60F7E7D00A5B0FF135B","SourceString":"Skill Upgrades","LocalizedString":"Skill Upgrades"}}}]