[{"Type":"WExpZoneDefinition","Name":"Zone_WaterfallValley_Map7","Class":"UScriptClass'WExpZoneDefinition'","Properties":{"ZoneName":{"Namespace":"","Key":"35F8D5FA4EA1675300A13581B09C4324","SourceString":"SECRET WATERFALL","LocalizedString":"SECRET WATERFALL"},"ZoneShortName":{"Namespace":"","Key":"5D0E9ABB42C6A1EDD3E306B236A6130A","SourceString":"18-7","LocalizedString":"18-7"},"ZoneDescription":{"Namespace":"","Key":"60D6CBFE43524F3700936C8A9CD54D34","SourceString":"Arctic temperatures increase hero CD.","LocalizedString":"Arctic temperatures increase hero CD."},"ZoneId":"Zone.WaterfallValley.Map7","LevelInstanceClass":{"AssetPathName":"/Game/World/Levels/B_LevelInst_WaterfallValley.B_LevelInst_WaterfallValley_C","SubPathString":""},"LevelInstanceComponentClasses":[{"AssetPathName":"/Game/World/Levels/Components/B_LIC_WaterfallValley.B_LIC_WaterfallValley_C","SubPathString":""}],"ZoneElement":"EWExpElement::Water","EntryCinematicScene":{"AssetPathName":"/Game/UMG/Story/Story/18-2_WaterfallValleyCont.18-2_WaterfallValleyCont_C","SubPathString":""},"ZoneMarkerConversation":"WaterfallSecret","TeamRequirements":{"Requirements":[{"Count":2,"HeroClass":"EWExpCharacterClass::AnyClass","HeroElement":"EWExpElement::Nature","HeroLevel":1}]},"ZoneMarkerBlueprintClass":{"AssetPathName":"/Game/Menus/WorldMap/UMGZoneMarker_BP.UMGZoneMarker_BP_C","SubPathString":""}}}]