[{"Type":"WExpRoomDefinition","Name":"R_Nightmare_FindExit","Class":"UScriptClass'WExpRoomDefinition'","Properties":{"RoomInstanceClass":{"AssetPathName":"/Game/World/Rooms/Element/B_RoomInst_Dark_Spooky.B_RoomInst_Dark_Spooky_C","SubPathString":""},"TileGenerator":{"ObjectName":"WExpTileGenerator'TG_Demo'","ObjectPath":"WorldExplorers/Content/World/Generation/Tiles/TG_Demo.0"},"OnEnterTitle":{"Namespace":"","Key":"F301912046155B40E67370AA1A62E82C","SourceString":"Death Awaits","LocalizedString":"Death Awaits"},"OnEnterMessage":{"Namespace":"","Key":"BF5DCC384E4134E8D3EF83AB3890C66E","SourceString":"Nightmare Room... escape if you can!","LocalizedString":"Nightmare Room... escape if you can!"},"OnEnterImage":{"ImageSize":{"X":64.0,"Y":64.0},"ResourceObject":{"ObjectName":"Texture2D'QTE_Icon_Crit_64'","ObjectPath":"WorldExplorers/Content/HUD/QuickTimeEvents/QTE_Icon_Crit_64.0"}},"CameraTransition":{"ObjectName":"WExpCameraTransitionAsset'DefaultRoomTransition'","ObjectPath":"WorldExplorers/Content/Camera/DefaultRoomTransition.0"},"BonusCameraTransition":{"ObjectName":"WExpCameraTransitionAsset'DefaultBonusRoomTransition'","ObjectPath":"WorldExplorers/Content/Camera/DefaultBonusRoomTransition.0"},"RoomObjective":"EWExpRoomObjective::FindExit"}}]