[{"Type":"MaterialParameterCollection","Name":"MPC_Map_Sun","Class":"UScriptClass'MaterialParameterCollection'","Properties":{"StateId":"AEC5F65A-4E93DDD1-1CF5D99A-70DCF7C9","ScalarParameters":[{"DefaultValue":2.5,"ParameterName":"DiffuseLightPower","Id":"DF276ACB-427D354A-6ABA2BAA-60A703B8"},{"DefaultValue":5.0,"ParameterName":"DiffuseShadowPower","Id":"BF947FBE-4453B6B7-B0CA2982-CA70A321"}],"VectorParameters":[{"DefaultValue":{"R":-0.1,"G":-2.0,"B":0.0,"A":0.0,"Hex":"000000"},"ParameterName":"LightDirection","Id":"1A2584B6-49160699-928D8CBE-F9F82E43"},{"DefaultValue":{"R":1.0,"G":0.912777,"B":0.843475,"A":0.0,"Hex":"FFF5ED"},"ParameterName":"LightColor","Id":"9A24340D-4138F07A-945A729D-58E61BD9"},{"DefaultValue":{"R":0.0,"G":0.0,"B":0.0,"A":0.0,"Hex":"000000"},"ParameterName":"FogColor","Id":"395D6A44-45953B0B-9DB04EB5-CA90F6A3"},{"DefaultValue":{"R":0.355,"G":0.273664,"B":0.184526,"A":0.0,"Hex":"A18F77"},"ParameterName":"ShadowColor","Id":"9E0E3145-458D88F3-C318418A-561B6FD4"}]}}]