[{"Type":"WExpZoneDefinition","Name":"Zone_ForestOfMixedEmotions_Map3","Class":"UScriptClass'WExpZoneDefinition'","Properties":{"ZoneName":{"Namespace":"","Key":"DE18C16341DAAE0854530AB506FA7413","SourceString":"NOT-SO HAPPY FOREST","LocalizedString":"NOT-SO HAPPY FOREST"},"ZoneShortName":{"Namespace":"","Key":"CE5049E94BCE8385EC8E77A1A0F9322B","SourceString":"1-3","LocalizedString":"1-3"},"ZoneId":"Zone.ForestOfMixedEmotions.Map3","LevelInstanceClass":{"AssetPathName":"/Game/World/Levels/Custom/B_LevelInst_Custom_ForestOfMixedEmotions_Map3_New.B_LevelInst_Custom_ForestOfMixedEmotions_Map3_New_C","SubPathString":""},"ZoneElement":"EWExpElement::Nature","TeamRequirements":{"MinPartySize":3},"HQBuildingRequirements":[{"BuildingDefinition":{"AssetPathName":"/Game/Menus/Headquarters/HQ_AncientFactory.HQ_AncientFactory","SubPathString":""},"LevelRequirement":1}],"TagSwaps":[{"towerDark":"Character:Mage_Basic_Dark_Sprite_T01"},{"towerFire":"Character:Mage_Basic_Fire_Sprite_T01"},{"towerLight":"Character:Mage_Basic_Light_Sprite_T01"},{"towerNature":"Character:Mage_Basic_Nature_Sprite_T01"},{"towerWater":"Character:Mage_Basic_Water_Sprite_T01"},{"trapDark":"Character:Assassin_C1_Dark_ImpStab_T01"},{"trapFire":"Character:Assassin_C1_Fire_ImpStab_T01"},{"trapLight":"Character:Assassin_C1_Light_ImpStab_T01"},{"trapNature":"Character:Assassin_C1_Nature_ImpStab_T01"},{"trapWater":"Character:Assassin_C1_Water_ImpStab_T01"}],"ZoneMarkerBlueprintClass":{"AssetPathName":"/Game/Menus/WorldMap/UMGZoneMarker_BP.UMGZoneMarker_BP_C","SubPathString":""},"OnLevelCompleteScript":[{"AssetPathName":"/Game/Campaign/Zones/ForestOfMixedEmotions/OnComplete_ForestOfMixedEmotions_Map3.OnComplete_ForestOfMixedEmotions_Map3_C","SubPathString":""}]}}]