[{"Type":"WExpGearAccountItemDefinition","Name":"GD_Weapon_OrbOfPower_Nature","Class":"UScriptClass'WExpGearAccountItemDefinition'","Properties":{"GearType":"EWExpGearType::Weapon","ElementType":"EWExpElement::Nature","Affixes":[{"ObjectName":"WExpGearAffix'AD_Base_Mana'","ObjectPath":"WorldExplorers/Content/Loot/AccountItems/Gear/AD_Base_Mana.0"},{"ObjectName":"WExpGearAffix'AD_Base_ATK'","ObjectPath":"WorldExplorers/Content/Loot/AccountItems/Gear/AD_Base_ATK.0"}],"IconTextureAssetData":{"AssetPathName":"/Game/UMG/Textures/HeroGear/T_Gear_Weapon_OrbOfPower_Nature.T_Gear_Weapon_OrbOfPower_Nature","SubPathString":""},"DisplayName":{"Namespace":"","Key":"8C34506F4028B10C2A978EB2B271BE15","SourceString":"Orb of Power","LocalizedString":"Orb of Power"}}}]