[{"Type":"WExpZoneDefinition","Name":"Zone_WC_Weekend_SB_MorrowLabs_3","Class":"UScriptClass'WExpZoneDefinition'","Properties":{"ZoneName":{"Namespace":"","Key":"246278AD40DC50A751DB2097F1637F84","SourceString":"Morrow Labs","LocalizedString":"Morrow Labs"},"ZoneDescription":{"Namespace":"","Key":"670BACBB48A4C5A163F64B82D1B97237","SourceString":"A somewhat notorious research institute obsessively involved in cutting edge biogenetics. Requirements: Dark, Nature, Assassin, Mage Knight, Shadow Knight ","LocalizedString":"A somewhat notorious research institute obsessively involved in cutting edge biogenetics. Requirements: Dark, Nature, Assassin, Mage Knight, Shadow Knight "},"ZoneType":"EWExpZoneType::Bonus","ZoneId":"Zone.Event.WC.Weekend.BossSuper.3.MorrowLabs.Map1","LevelInstanceClass":{"AssetPathName":"/Game/World/Levels/B_LevelInst_Master.B_LevelInst_Master_C","SubPathString":""},"ServerZoneType":"EWExpMcpZoneType::WeeklyChallengeBoss","LevelArtOverride":{"AssetPathName":"/Game/Campaign/Regions/LevelArt_WeeklyChallenge1.LevelArt_WeeklyChallenge1","SubPathString":""},"BannerMat":{"AssetPathName":"/Game/UMG/Story/Events/Generic/Banners/M_Event_Banner_Dark_01.M_Event_Banner_Dark_01","SubPathString":""},"BorderMat":{"AssetPathName":"/Game/UMG/Story/Events/Generic/Borders/M_Event_Weekly_TKVoucher.M_Event_Weekly_TKVoucher","SubPathString":""},"ZoneMarkerBlueprintClass":{"AssetPathName":"/Game/Menus/WorldMap/UMGZoneMarker_BP.UMGZoneMarker_BP_C","SubPathString":""}}}]