[{"Type":"WExpZoneDefinition","Name":"Zone_WC_Weekend_SB_TundraWalkers_3","Class":"UScriptClass'WExpZoneDefinition'","Properties":{"ZoneName":{"Namespace":"","Key":"71493FC04B985430A53CDDB5541B8834","SourceString":"Tundra Walkers","LocalizedString":"Tundra Walkers"},"ZoneDescription":{"Namespace":"","Key":"885C6804427B6C82FD6E6BBCA720B645","SourceString":"A nomadic collection of hardened warriors that are fierce allies of the world. Requirements: Dark, Water, Dragon Knight, Treasure Hunter, Warrior ","LocalizedString":"A nomadic collection of hardened warriors that are fierce allies of the world. Requirements: Dark, Water, Dragon Knight, Treasure Hunter, Warrior "},"ZoneType":"EWExpZoneType::Bonus","ZoneId":"Zone.Event.WC.Weekend.BossSuper.3.TundraWalkers.Map1","LevelInstanceClass":{"AssetPathName":"/Game/World/Levels/B_LevelInst_Master.B_LevelInst_Master_C","SubPathString":""},"ServerZoneType":"EWExpMcpZoneType::WeeklyChallengeBoss","LevelArtOverride":{"AssetPathName":"/Game/Campaign/Regions/LevelArt_WeeklyChallenge1.LevelArt_WeeklyChallenge1","SubPathString":""},"BannerMat":{"AssetPathName":"/Game/UMG/Story/Events/Generic/Banners/M_Event_Banner_Water_01.M_Event_Banner_Water_01","SubPathString":""},"BorderMat":{"AssetPathName":"/Game/UMG/Story/Events/Generic/Borders/M_Event_Weekly_TKVoucher.M_Event_Weekly_TKVoucher","SubPathString":""},"ZoneMarkerBlueprintClass":{"AssetPathName":"/Game/Menus/WorldMap/UMGZoneMarker_BP.UMGZoneMarker_BP_C","SubPathString":""}}}]