[
    {
        "Type": "FortCardPackItemDefinition",
        "Name": "CardPack_Silver",
        "Properties": {
            "bIsLlama": true,
            "LootTierGroup": "CardPack_Silver",
            "DisplayRarityLevel": 1,
            "PackPersonality": {
                "AssetPathName": "/Game/Characters/Feedback/Llama_Happy_PersonalityPack.Llama_Happy_PersonalityPack",
                "SubPathString": ""
            },
            "DisplayName": {
                "Namespace": "",
                "Key": "CCD582804BDFA81D797E9AA98896F697",
                "SourceString": "Silver Pack"
            },
            "Description": {
                "Namespace": "",
                "Key": "F35E21F146C3AEF8CACE73B94949DDFF",
                "SourceString": "Full of high quality stuff."
            },
            "SmallPreviewImage": {
                "AssetPathName": "/Game/UI/Frontend/Store/Textures/PinataStandardPack_128.PinataStandardPack_128",
                "SubPathString": ""
            },
            "LargePreviewImage": {
                "AssetPathName": "/Game/UI/Frontend/Store/Textures/PinataStandardPack.PinataStandardPack",
                "SubPathString": ""
            },
            "Rarity": "EFortRarity::Epic",
            "FrontendPreviewPivotOffset": {
                "X": 0.0,
                "Y": 0.0,
                "Z": -14.0
            },
            "FrontendPreviewInitialRotation": {
                "Pitch": 0.0,
                "Yaw": 83.20067,
                "Roll": 0.0
            },
            "FrontendPreviewMeshOverride": {
                "AssetPathName": "/Game/UI/Frontend/ItemInspect/Workers/S-WorkersPhotos.S-WorkersPhotos",
                "SubPathString": ""
            }
        }
    }
]