[{"Type":"WExpHelpData","Name":"H_Heroes_Foil","Class":"UScriptClass'WExpHelpData'","Properties":{"HelpSection":{"Title":{"Namespace":"","Key":"CD0458D648C98CDD3151BA9937AD37D5","SourceString":"Foil Heroes","LocalizedString":"Foil Heroes"},"Description":{"Namespace":"","Key":"9796C4E240207A6EC2A5E68D8751E224","SourceString":"You may be fortunate enough to obtain a foil version of a hero. On top of their flashy appearance, foil heroes are more valuable in the Monster Pit. Selling a foil hero while you do not have a foil hero in the Monster Pit will make the hero in the pit become foil. If you sell a hero who is foil while you have a foil copy in the pit, you will be given Molten Foil that will allow you make other heroes foil.","LocalizedString":"You may be fortunate enough to obtain a foil version of a hero. On top of their flashy appearance, foil heroes are more valuable in the Monster Pit. Selling a foil hero while you do not have a foil hero in the Monster Pit will make the hero in the pit become foil. If you sell a hero who is foil while you have a foil copy in the pit, you will be given Molten Foil that will allow you make other heroes foil."},"ImageAssetData":{"AssetPathName":"/Game/UMG/Textures/Icons/Items/T_Foil.T_Foil","SubPathString":""}}}}]