[{"Type":"WExpGiftboxDefinition","Name":"GB_LoginBonus_D13","Class":"UScriptClass'WExpGiftboxDefinition'","Properties":{"Message":{"Namespace":"","Key":"0C0F428C47179BF9040182BF529770B4","SourceString":"Here's an item you missed from the bonus login reward period!","LocalizedString":"Here's an item you missed from the bonus login reward period!"},"Loot":{"Items":[{"ItemType":"Giftbox:GB_LoginBonus_D14","ItemGuid":"","Quantity":1,"Attributes":{"JsonString":""},"ItemProfile":""},{"ItemType":"Currency:MtxGiveaway","ItemGuid":"","Quantity":250,"Attributes":{"JsonString":""},"ItemProfile":""}]},"SealBoxForDays":1,"Rarity":"EWExpRarity::VeryRare","SortPriority":10000,"IconTextureAssetData":{"AssetPathName":"/Game/UMG/Textures/Icons/Items/T_Chest_GiftBox_Small.T_Chest_GiftBox_Small","SubPathString":""},"Description":{"Namespace":"","Key":"3CA59DF245414C64F5D47D9AE1EE40C6","SourceString":"Rewards for logging in!","LocalizedString":"Rewards for logging in!"},"DisplayName":{"Namespace":"","Key":"EF6B11CB4081B5DB59E2D9986E6007E8","SourceString":"Login Bonus Day 13","LocalizedString":"Login Bonus Day 13"}}}]